redpepper/operations/__init__.py
redpepper/operations/apt.py
redpepper/operations/command.py
redpepper/operations/custom.py
redpepper/operations/data.py
redpepper/operations/echo.py
redpepper/operations/file.py
redpepper/operations/git.py
redpepper/operations/noop.py
redpepper/operations/package.py
redpepper/operations/py.py
redpepper/operations/request.py
redpepper/operations/service.py
redpepper/operations/sysctl.py
redpepper/operations/systemd.py
redpepper_operations-0.3.3.dist-info/METADATA
redpepper_operations-0.3.3.dist-info/WHEEL
redpepper_operations-0.3.3.dist-info/RECORD
